LICENSE
incolumepy/makefilelicense/__init__.py
incolumepy/makefilelicense/exceptions/__init__.py
incolumepy/makefilelicense/licenses/agpl.txt
incolumepy/makefilelicense/licenses/apache.txt
incolumepy/makefilelicense/licenses/bsl.txt
incolumepy/makefilelicense/licenses/cc0.txt
incolumepy/makefilelicense/licenses/gpl.txt
incolumepy/makefilelicense/licenses/lgpl.txt
incolumepy/makefilelicense/licenses/mit.txt
incolumepy/makefilelicense/licenses/mpl.txt
incolumepy/makefilelicense/licenses/unlicense.txt
incolumepy/makefilelicense/licenses.py
incolumepy/makefilelicense/version.txt
pyproject.toml
incolumepy.makefilelicense-0.3.1.dist-info/entry_points.txt
incolumepy.makefilelicense-0.3.1.dist-info/LICENSE
incolumepy.makefilelicense-0.3.1.dist-info/WHEEL
incolumepy.makefilelicense-0.3.1.dist-info/METADATA
incolumepy.makefilelicense-0.3.1.dist-info/RECORD
