Metadata-Version: 2.1
Name: incolumepy.makefilelicense
Version: 0.3.1
Summary: This software take a License and agregate into the project.
License: MIT
Keywords: licenses,projects,utilities
Author: Britodfbr
Author-email: britodfbr@gmail.com
Maintainer: Britodfbr
Maintainer-email: britodfbr@gmail.com
Requires-Python: >=3.6.8,<4.0
Classifier: Development Status :: 5 - Production/Stable
Classifier: Environment :: Console
Classifier: Environment :: Plugins
Classifier: License :: Free For Educational Use
Classifier: License :: Free For Home Use
Classifier: License :: OSI Approved :: MIT License
Classifier: Operating System :: OS Independent
Classifier: Programming Language :: Python
Classifier: Programming Language :: Python :: 3
Classifier: Programming Language :: Python :: 3 :: Only
Classifier: Programming Language :: Python :: 3.10
Classifier: Programming Language :: Python :: 3.6
Classifier: Programming Language :: Python :: 3.7
Classifier: Programming Language :: Python :: 3.8
Classifier: Programming Language :: Python :: 3.9
Classifier: Programming Language :: Python :: Implementation
Classifier: Topic :: Software Development
Classifier: Topic :: Software Development :: Build Tools
Classifier: Topic :: Software Development :: Code Generators
Classifier: Topic :: Software Development :: Documentation
Classifier: Topic :: Software Development :: Libraries :: Python Modules
Classifier: Topic :: System :: Installation/Setup
Classifier: Topic :: Utilities
Requires-Dist: importlib-metadata; python_version < "3.8"
Requires-Dist: toml[tomli] (>=0.10.2,<0.11.0); python_version >= "3.6" and python_version < "4.0"
Project-URL: Bug Tracker, https://github.com/incolumepy/incolumepy.makefilelicense/issues
Project-URL: homepage, https://pypi.org/project/incolumepy.makefilelicense
Project-URL: license, https://github.com/incolumepy/incolumepy.makefilelicense/blob/main/LICENSE
Project-URL: repository, https://github.com/incolumepy/incolumepy.makefilelicense
